README.md
WEBSOCKET_API.md
requirements.txt
neuro_simulator/__init__.py
neuro_simulator/cli.py
neuro_simulator/agents/__init__.py
neuro_simulator/agents/llm.py
neuro_simulator/agents/streaming_parser.py
neuro_simulator/agents/chatbot/__init__.py
neuro_simulator/agents/chatbot/core.py
neuro_simulator/agents/chatbot/memory/__init__.py
neuro_simulator/agents/chatbot/memory/core_memory.json
neuro_simulator/agents/chatbot/memory/init_memory.json
neuro_simulator/agents/chatbot/memory/temp_memory.json
neuro_simulator/agents/chatbot/nickname_gen/__init__.py
neuro_simulator/agents/chatbot/nickname_gen/generator.py
neuro_simulator/agents/chatbot/nickname_gen/data/adjectives.txt
neuro_simulator/agents/chatbot/nickname_gen/data/nouns.txt
neuro_simulator/agents/chatbot/nickname_gen/data/special_users.txt
neuro_simulator/agents/chatbot/prompts/__init__.py
neuro_simulator/agents/chatbot/prompts/ambient_prompt.txt
neuro_simulator/agents/chatbot/prompts/chatbot_prompt.txt
neuro_simulator/agents/chatbot/prompts/memory_prompt.txt
neuro_simulator/agents/chatbot/tools/__init__.py
neuro_simulator/agents/chatbot/tools/add_temp_memory.py
neuro_simulator/agents/chatbot/tools/add_to_core_memory_block.py
neuro_simulator/agents/chatbot/tools/create_core_memory_block.py
neuro_simulator/agents/chatbot/tools/delete_core_memory_block.py
neuro_simulator/agents/chatbot/tools/get_core_memory_block.py
neuro_simulator/agents/chatbot/tools/get_core_memory_blocks.py
neuro_simulator/agents/chatbot/tools/post_chat_message.py
neuro_simulator/agents/chatbot/tools/remove_from_core_memory_block.py
neuro_simulator/agents/chatbot/tools/update_core_memory_block.py
neuro_simulator/agents/memory/manager.py
neuro_simulator/agents/neuro/__init__.py
neuro_simulator/agents/neuro/core.py
neuro_simulator/agents/neuro/filter/filter.py
neuro_simulator/agents/neuro/memory/__init__.py
neuro_simulator/agents/neuro/memory/chat_history.json
neuro_simulator/agents/neuro/memory/core_memory.json
neuro_simulator-0.6.11.dist-info/METADATA
neuro_simulator-0.6.11.dist-info/WHEEL
neuro_simulator-0.6.11.dist-info/entry_points.txt
neuro_simulator-0.6.11.dist-info/licenses/LICENSE
neuro_simulator-0.6.11.dist-info/RECORD
