Metadata-Version: 2.4
Name: neuro_simulator
Version: 0.6.11
Summary: Neuro Simulator Server
Project-URL: Homepage, https://github.com/Moha-Master/neuro-simulator
Project-URL: Repository, https://github.com/Moha-Master/neuro-simulator
Project-URL: Issues, https://github.com/Moha-Master/neuro-simulator/issues
Author-email: Moha-Master <hongkongreporter@outlook.com>
License-Expression: MIT
License-File: LICENSE
Classifier: Development Status :: 4 - Beta
Classifier: Intended Audience :: Developers
Classifier: Operating System :: OS Independent
Classifier: Programming Language :: Python :: 3
Classifier: Programming Language :: Python :: 3.8
Classifier: Programming Language :: Python :: 3.9
Classifier: Programming Language :: Python :: 3.10
Classifier: Programming Language :: Python :: 3.11
Classifier: Programming Language :: Python :: 3.12
Classifier: Programming Language :: Python :: 3.13
Requires-Python: >=3.8
Requires-Dist: azure-cognitiveservices-speech
Requires-Dist: fastapi
Requires-Dist: google-genai
Requires-Dist: httpx[socks]
Requires-Dist: jinja2
Requires-Dist: mutagen
Requires-Dist: openai
Requires-Dist: pydantic
Requires-Dist: python-multipart
Requires-Dist: pyyaml
Requires-Dist: uvicorn
Provides-Extra: dev
Requires-Dist: black; extra == 'dev'
Requires-Dist: flake8; extra == 'dev'
Requires-Dist: pytest-cov; extra == 'dev'
Requires-Dist: pytest>=6.0; extra == 'dev'
